[{
    "type": "internal",
    "trans": "menu.home",
    "route": "public.posts",
    "icon": "icon ion-home"
}, {
    "type": "separator",
    "trans": "Quick Links"
}, {
    "type": "external",
    "trans": "The Roeper School Website",
    "href": "https://www.roeper.org",
    "icon": "icon ion-home"
}, {
    "type": "external",
    "trans": "Edmodo",
    "href": "https://www.edmodo.com",
    "icon": "icon ion-ios-people"
}, {
    "type": "external",
    "trans": "PaySchools",
    "href": "https://parent.payschools.com/categories.asp?id=95DB16FEF60E4303882A3A506FCED3C4",
    "icon": "icon ion-social-usd"
}, {
    "type": "external",
    "trans": "NetClassroom",
    "href": "http://blmw1.roeper.org/NetClassroom7/Forms/login.aspx",
    "icon": "icon ion-android-list"
}, {
    "type": "external",
    "trans": "Faculty Access Web",
    "href": "http://blmw1.roeper.org/FAWeb7/forms/login.aspx",
    "icon": "icon ion-edit"
}, {
    "type": "separator",
    "trans": "More"
}, {
    "type": "internal",
    "trans": "menu.authors",
    "route": "public.authors",
    "icon": "icon ion-ios-people"
}, {
    "type": "internal",
    "trans": "menu.bookmarks",
    "route": "public.bookmarks",
    "icon": "icon ion-bookmark"
}, {
    "type": "internal",
    "trans": "params.title",
    "route": "public.params",
    "icon": "icon ion-gear-b"
}]